pytypeutils/__init__.py
pytypeutils/np_checks.py
pytypeutils/torch_checks.py
pytypeutils/utils.py
pytypeutils-0.0.1.dist-info/LICENSE.txt
pytypeutils-0.0.1.dist-info/METADATA
pytypeutils-0.0.1.dist-info/WHEEL
pytypeutils-0.0.1.dist-info/top_level.txt
pytypeutils-0.0.1.dist-info/RECORD
