Metadata-Version: 2.1
Name: pytypeutils
Version: 0.0.1
Summary: Runtime typechecking without annotations
Home-page: https://github.com/tjstretchalot/pytypeutils
Author: Timothy Moore
Author-email: mtimothy984@gmail.com
License: CC0
Keywords: pytypeutils typechecking
Platform: UNKNOWN
Classifier: Programming Language :: Python :: 3
Classifier: Programming Language :: Python :: 3.6
Classifier: Programming Language :: Python :: 3.7
Classifier: License :: CC0 1.0 Universal (CC0 1.0) Public Domain Dedication
Classifier: Topic :: Utilities
Requires-Python: >=3.6
Provides-Extra: test
Requires-Dist: numpy ; extra == 'test'
Requires-Dist: torch ; extra == 'test'
